gradle.properties
hexdoc_moreiotas/__gradle_version__.py
hexdoc_moreiotas/__init__.py
hexdoc_moreiotas/__version__.py
hexdoc_moreiotas/_hooks.py
hexdoc_moreiotas/py.typed
hexdoc_moreiotas/_export/.gitignore
hexdoc_moreiotas/_export/__init__.py
hexdoc_moreiotas/_export/generated/__init__.py
hexdoc_moreiotas/_export/generated/moreiotas.hexdoc.json
hexdoc_moreiotas/_export/generated/moreiotas.patterns.hexdoc.json
hexdoc_moreiotas/_export/generated/assets/hexcasting/patchouli_books/thehexbook/en_us/entries/casting/item_iotas.json
hexdoc_moreiotas/_export/generated/assets/hexcasting/patchouli_books/thehexbook/en_us/entries/patterns/items.json
hexdoc_moreiotas/_export/generated/assets/hexcasting/patchouli_books/thehexbook/en_us/entries/patterns/matrices.json
hexdoc_moreiotas/_export/generated/assets/hexcasting/patchouli_books/thehexbook/en_us/entries/patterns/strings.json
hexdoc_moreiotas/_export/generated/assets/hexcasting/patchouli_books/thehexbook/en_us/entries/patterns/types.json
hexdoc_moreiotas/_export/generated/assets/moreiotas/lang/en_us.flatten.json5
hexdoc_moreiotas/_export/generated/assets/moreiotas/lang/en_us.json
hexdoc_moreiotas/_export/generated/assets/moreiotas/lang/zh_cn.json
hexdoc_moreiotas/_templates/__init__.py
hexdoc_moreiotas-0.1.1.1.0.dist-info/METADATA
hexdoc_moreiotas-0.1.1.1.0.dist-info/WHEEL
hexdoc_moreiotas-0.1.1.1.0.dist-info/entry_points.txt
hexdoc_moreiotas-0.1.1.1.0.dist-info/licenses/LICENSE.txt
hexdoc_moreiotas-0.1.1.1.0.dist-info/RECORD
