Metadata-Version: 2.4
Name: hexdoc-moreiotas
Version: 0.1.1.1.0
Summary: Python web book docgen and hexdoc plugin for MoreIotas.
Project-URL: Homepage, https://moreiotas.hexxy.media
Project-URL: Source, https://github.com/FallingColors/MoreIotas
Author: Falling Colors, Talia-12
License-File: LICENSE.txt
Keywords: hexdoc
Requires-Python: >=3.11
Requires-Dist: hexdoc-hexcasting~=0.11.2.1.0
Provides-Extra: dev
Requires-Dist: ruff~=0.11.2; extra == 'dev'
